{
  "plans": {
    "YILMAZ USTA": {
      "1": [
        "GIRESUN MERKEZ -1",
        [
          "GIRESUN MERKEZ -1",
          "GIRESUN MERKEZ -2"
        ],
        [
          "ORDU MERKEZ -1",
          "ORDU MERKEZ -2",
          "ORDU MERKEZ -3"
        ],
        [
          "GIRESUN BULANCAK+PIRAZIZ",
          "ORDU FATSA"
        ],
        [
          "ORDU BATI ILCELER",
          "ORDU GUNEY ILCELER -1"
        ],
        [
          "GIRESUN BULANCAK+PIRAZIZ"
        ]
      ],
      "2": [
        "ORDU MERKEZ -1",
        [
          "GIRESUN MERKEZ -1",
          "GIRESUN MERKEZ -2"
        ],
        [
          "ORDU MERKEZ -1",
          "ORDU MERKEZ -2",
          "ORDU MERKEZ -3"
        ],
        [
          "ORDU FATSA"
        ],
        [
          "ORDU DOGU ILCELER"
        ],
        [
          "GIRESUN BULANCAK+PIRAZIZ"
        ]
      ],
      "3": [
        "GIRESUN BULANCAK+PIRAZIZ",
        "ORDU FATSA"
      ],
      "4": [
        "ORDU BATI ILCELER",
        "ORDU DOGU ILCELER",
        "ORDU GUNEY ILCELER -1"
      ],
      "5": [
        "GIRESUN BULANCAK+PIRAZIZ",
        "GIRESUN MERKEZ -1",
        "GIRESUN MERKEZ -2"
      ]
    },
    "AYKUT D횄혘횂혘횄혗횂혘횄혘횂혗횄혗횂혘횄혘횂혘횄혗횂혗횄혘횂혗횄혗횂혘횄혘횂혘횄혗횂혘횄혘횂혗횄혗횂혗횄혘횂혘횄혗횂혗횄혘횂혗횄혗횂혙횄혘횂혘횄혗횂혘횄혘횂혗횄혗횂혘횄혘횂혘횄혗횂혗횄혘횂혗횄혗횂혗횄혘횂혘횄혗횂혘횄혘횂혗횄혗횂혗횄혘횂혘횄혗횂혗횄혘횂혗횄혗횂째NLER": {
      "1": {
        "1": [
          "AMASYA MERKEZ -1",
          "AMASYA MERKEZ -2"
        ]
      }
    },
    "AYKUT D횄혘횂혘횄혗횂혘횄혘횂혗횄혗횂혘횄혘횂혘횄혗횂혗횄혘횂혗횄혗횂혙횄혘횂혘횄혗횂혘횄혘횂혗횄혗횂혗횄혘횂혘횄혗횂혗횄혘횂혗횄혗횂째NLER": {
      "1": {
        "2": [
          "CORUM GUNEYBATI ILCELER",
          "CORUM GUNEYDOGU ILCELER",
          "CORUM KARGI+OSMANCIK"
        ]
      }
    },
    "AYKUT D횄혘횂혘횄혗횂혘횄혘횂혗횄혗횂혙횄혘횂혘횄혗횂혗횄혘횂혗횄혗횂째NLER": {
      "1": {
        "3": [
          "CORUM KUZEY ILCELER"
        ]
      }
    },
    "AYKUT D횄혘횂혘횄혗횂혙횄혘횂혗횄혗횂째NLER": {
      "1": {
        "4": [
          "AMASYA ILCELER",
          "AMASYA MERZIFON"
        ]
      }
    },
    "AYKUT D횄혘횂혙횄혗횂째NLER": {
      "1": {
        "5": [
          "CORUM MERKEZ -1",
          "CORUM MERKEZ -2",
          "CORUM MERKEZ -3"
        ]
      }
    },
    "AYKUT D횄혙횂째NLER": {
      "2": {
        "1": [
          "AMASYA MERKEZ -1",
          "AMASYA MERKEZ -2"
        ]
      }
    },
    "AYKUT D횆째NLER": {
      "2": {
        "2": []
      }
    },
    "AYKUT D캅NLER": {
      "2": {
        "3": []
      }
    }
  },
  "updatedAt": "2026-07-19T23:09:17.346Z"
}